<?xml version="1.0" encoding="utf-8"?>
<Files clsid="{215B2E53-57CE-475c-80FE-9EEC14635851}">
	<File clsid="{50BE44C8-567A-4ed1-B1D0-9234FE1F38AF}" name="" status="" image="1" changed="2025-04-04 15:22:23" uid="{893428A5-D83D-438E-8941-290538F31138}" desc="Copy files for GPO HAD-TS-LocalAdminGroups" bypassErrors="1">
		<Properties action="R" fromPath="\\HARDEN.AD\netlogon\HardenAD\HAD-TS-Local-admins-groups\Set-LocalAdminGroups\*.ps1" targetPath="%windir%\HardenAD\ScheduledTasks\Set-LocalAdminGroups\" readOnly="0" archive="0" hidden="0" suppress="0"/>
		<Filters>
			<FilterRunOnce hidden="1" not="0" bool="AND" id="{5E9B8C9B-8D5A-4E5B-9063-B07A0780C39D}"/>
		</Filters>
	</File>
	<File clsid="{50BE44C8-567A-4ed1-B1D0-9234FE1F38AF}" name="" status="" image="1" changed="2025-02-26 18:44:00" uid="{5A6AB013-B92A-40C7-8EE6-C6BF055B9E78}" bypassErrors="1">
		<Properties action="R" fromPath="\\HARDEN.AD\netlogon\HardenAD\HAD-TS-Local-admins-groups\Event-Viewer\*" targetPath="%ProgramData%\Microsoft\Event Viewer\Views\HARDEN.AD\" readOnly="1" archive="0" hidden="0" suppress="0"/>
		<Filters>
			<FilterRunOnce hidden="1" not="0" bool="AND" id="{842295C3-9D9A-4D85-91CE-3223FB016D11}"/>
		</Filters>
	</File>
</Files>

