<Backups xmlns="http://www.microsoft.com/GroupPolicy/GPOOperations/Manifest" xmlns:mfst="http://www.microsoft.com/GroupPolicy/GPOOperations/Manifest" mfst:version="1.0"><BackupInst><GPOGuid><![CDATA[{7214E386-2A89-4111-9F10-F0F705089406}]]></GPOGuid><GPODomain><![CDATA[HARDEN.AD]]></GPODomain><GPODomainGuid><![CDATA[{7e6d5aed-2e60-432c-8a62-699f13d60c24}]]></GPODomainGuid><GPODomainController><![CDATA[DC-01.HARDEN.AD]]></GPODomainController><BackupTime><![CDATA[2025-03-04T10:09:47]]></BackupTime><ID><![CDATA[{AD0FA494-5503-4C5F-8C18-1579B6572BAC}]]></ID><Comment><![CDATA[]]></Comment><GPODisplayName><![CDATA[HAD-LocalRDU-T1]]></GPODisplayName></BackupInst></Backups>